LICENSE
README.md
pyproject.toml
setup.py
src/spins_utilz.egg-info/PKG-INFO
src/spins_utilz.egg-info/SOURCES.txt
src/spins_utilz.egg-info/dependency_links.txt
src/spins_utilz.egg-info/requires.txt
src/spins_utilz.egg-info/top_level.txt
src/utilz/__init__.py
src/utilz/layers.py
src/utilz/modes.py
src/utilz/shapes.py
src/utilz/utilz_version.py
tests/test_integration.py
tests/test_layers.py
tests/test_modes.py
tests/test_shapes.py