Metadata-Version: 2.1
Name: spins-utilz
Version: 1.0.1
Summary: Utilities for differentiable computational photonics
Home-page: https://github.com/spinsphotonics/utilz
Author: Jesse Lu
Author-email: jesselu@spinsphotonics.com
License: MIT
Platform: UNKNOWN
Provides-Extra: test
License-File: LICENSE
